dungngo_k8s_mcp_server-1.3.3.dist-info/licenses/LICENSE
k8s_mcp_server/__init__.py
k8s_mcp_server/__main__.py
k8s_mcp_server/cli_executor.py
k8s_mcp_server/config.py
k8s_mcp_server/errors.py
k8s_mcp_server/prompts.py
k8s_mcp_server/security.py
k8s_mcp_server/server.py
k8s_mcp_server/tools.py
dungngo_k8s_mcp_server-1.3.3.dist-info/METADATA
dungngo_k8s_mcp_server-1.3.3.dist-info/WHEEL
dungngo_k8s_mcp_server-1.3.3.dist-info/top_level.txt
dungngo_k8s_mcp_server-1.3.3.dist-info/RECORD
