Metadata-Version: 2.4
Name: dungngo-k8s-mcp-server
Version: 1.3.3
Summary: MCP Server for Kubernetes CLI tools (kubectl, istioctl, helm, argocd) (republished for testing)
Author-email: dungngo <test@dungngo.dev>
License: MIT
Classifier: Programming Language :: Python :: 3
Classifier: License :: OSI Approved :: MIT License
Classifier: Operating System :: OS Independent
Requires-Python: >=3.13
License-File: LICENSE
Requires-Dist: mcp
Requires-Dist: pydantic>=2.0.0
Requires-Dist: psutil>=5.9.0
Requires-Dist: pyyaml>=6.0.0
Provides-Extra: dev
Requires-Dist: ruff; extra == "dev"
Requires-Dist: pytest; extra == "dev"
Requires-Dist: pytest-asyncio; extra == "dev"
Requires-Dist: pytest-cov; extra == "dev"
Dynamic: license-file
